ua_parser/__init__.py
ua_parser/_regexes.py
ua_parser/user_agent_parser.py
ua_parser/user_agent_parser_test.py
ua_parser-0.18.0.dist-info/METADATA
ua_parser-0.18.0.dist-info/WHEEL
ua_parser-0.18.0.dist-info/top_level.txt
ua_parser-0.18.0.dist-info/RECORD
